Metadata-Version: 2.4
Name: ydata-profiling-multilingual
Version: 1.0.7
Summary: forked from ydataai/ydata-profiling and modify the code to support international multilingual functionality
Home-page: https://github.com/landonzeng/ydata-profiling-multilingual
Author: Landon Zeng
Author-email: YData Labs Inc <opensource@ydata.ai>, landonzeng <landonzeng@qq.com>
License: The MIT License (MIT)
Project-URL: Homepage, https://github.com/landonzeng/ydata-profiling-multilingual
Project-URL: Repository, https://github.com/landonzeng/ydata-profiling-multilingual
Project-URL: Original Repository, https://github.com/ydataai/ydata-profiling
Keywords: pandas,data-science,data-analysis,python,jupyter,ipython,i18n,multilingual,ydata-profiling-fork
Classifier: Development Status :: 5 - Production/Stable
Classifier: Topic :: Software Development :: Build Tools
Classifier: License :: OSI Approved :: MIT License
Classifier: Environment :: Console
Classifier: Operating System :: OS Independent
Classifier: Intended Audience :: Science/Research
Classifier: Intended Audience :: Developers
Classifier: Intended Audience :: Financial and Insurance Industry
Classifier: Intended Audience :: Healthcare Industry
Classifier: Topic :: Scientific/Engineering
Classifier: Framework :: IPython
Classifier: Programming Language :: Python :: 3
Classifier: Programming Language :: Python :: 3.7
Classifier: Programming Language :: Python :: 3.8
Classifier: Programming Language :: Python :: 3.9
Classifier: Programming Language :: Python :: 3.10
Classifier: Programming Language :: Python :: 3.11
Classifier: Programming Language :: Python :: 3.12
Requires-Python: >=3.8
License-File: LICENSE
Requires-Dist: scipy<1.16,>=1.4.1
Requires-Dist: pandas!=1.4.0,<3.0,>1.1
Requires-Dist: matplotlib<=3.10,>=3.5
Requires-Dist: pydantic>=2
Requires-Dist: PyYAML<6.1,>=5.0.0
Requires-Dist: jinja2<3.2,>=2.11.1
Requires-Dist: visions[type_image_path]<0.8.2,>=0.7.5
Requires-Dist: numpy<2.2,>=1.16.0
Requires-Dist: htmlmin==0.1.12
Requires-Dist: phik<0.13,>=0.11.1
Requires-Dist: requests<3,>=2.24.0
Requires-Dist: tqdm<5,>=4.48.2
Requires-Dist: seaborn<0.14,>=0.10.1
Requires-Dist: multimethod<2,>=1.4
Requires-Dist: statsmodels<1,>=0.13.2
Requires-Dist: typeguard<5,>=3
Requires-Dist: imagehash==4.3.1
Requires-Dist: wordcloud>=1.9.3
Requires-Dist: dacite>=1.8
Requires-Dist: numba<=0.61,>=0.56.0
Requires-Dist: click>=7.0
Provides-Extra: dev
Requires-Dist: black>=20.8b1; extra == "dev"
Requires-Dist: isort>=5.0.7; extra == "dev"
Requires-Dist: pre-commit>=2.8.2; extra == "dev"
Requires-Dist: virtualenv>=20.0.33; extra == "dev"
Requires-Dist: twine; extra == "dev"
Requires-Dist: wheel; extra == "dev"
Requires-Dist: myst-parser>=0.18.1; extra == "dev"
Requires-Dist: sphinx_rtd_theme>=0.4.3; extra == "dev"
Requires-Dist: sphinx-autodoc-typehints>=1.10.3; extra == "dev"
Requires-Dist: sphinx-multiversion>=0.2.3; extra == "dev"
Requires-Dist: autodoc_pydantic; extra == "dev"
Provides-Extra: docs
Requires-Dist: mkdocs<1.7.0,>=1.6.0; extra == "docs"
Requires-Dist: mkdocs-material<10.0.0,>=9.0.12; extra == "docs"
Requires-Dist: mkdocs-material-extensions<2.0.0,>=1.1.1; extra == "docs"
Requires-Dist: mkdocs-table-reader-plugin<=2.2.0; extra == "docs"
Requires-Dist: mike<2.2.0,>=2.1.1; extra == "docs"
Requires-Dist: mkdocstrings[python]<1.0.0,>=0.20.0; extra == "docs"
Requires-Dist: mkdocs-badges; extra == "docs"
Provides-Extra: notebook
Requires-Dist: jupyter>=1.0.0; extra == "notebook"
Requires-Dist: ipywidgets>=7.5.1; extra == "notebook"
Provides-Extra: spark
Requires-Dist: pyspark>=3.0; extra == "spark"
Requires-Dist: pyarrow>=4.0.0; extra == "spark"
Requires-Dist: pandas>1.1; extra == "spark"
Requires-Dist: numpy>=1.16.0; extra == "spark"
Requires-Dist: visions[type_image_path]<0.7.7,>=0.7.5; extra == "spark"
Provides-Extra: test
Requires-Dist: pytest; extra == "test"
Requires-Dist: coverage<8,>=6.5; extra == "test"
Requires-Dist: codecov; extra == "test"
Requires-Dist: pytest-cov; extra == "test"
Requires-Dist: nbval; extra == "test"
Requires-Dist: pyarrow; extra == "test"
Requires-Dist: twine>=3.1.1; extra == "test"
Requires-Dist: kaggle; extra == "test"
Provides-Extra: unicode
Requires-Dist: tangled-up-in-unicode==0.2.0; extra == "unicode"
Dynamic: author
Dynamic: home-page
Dynamic: license-file
Dynamic: requires-python
